bel2scm/__init__.py
bel2scm/causal_graph.py
bel2scm/gen_test_data.py
bel2scm/graph_node.py
pyro_cg/__init__.py
pyro_cg/causal_graph.py
pyro_cg/cg_node.py
pyro_cg/gen_test_data.py
pyro_cg/graph_node.py
bel2scm-0.0.4.dist-info/LICENSE
bel2scm-0.0.4.dist-info/METADATA
bel2scm-0.0.4.dist-info/WHEEL
bel2scm-0.0.4.dist-info/top_level.txt
bel2scm-0.0.4.dist-info/RECORD
